phonemeRecognizerWrapper/__init__.py
phonemeRecognizerWrapper/recognize.py
phonemeRecognizerWrapper-0.1.4.dist-info/LICENSE.txt
phonemeRecognizerWrapper-0.1.4.dist-info/METADATA
phonemeRecognizerWrapper-0.1.4.dist-info/WHEEL
phonemeRecognizerWrapper-0.1.4.dist-info/top_level.txt
phonemeRecognizerWrapper-0.1.4.dist-info/RECORD
