Metadata-Version: 2.1
Name: phonemeRecognizerWrapper
Version: 0.1.4
Summary: Package containing one wrapper script over the Allosaurus phoneme recognition library, designed for passing the Allosaurus output data to MATLAB scripts for further analysis.
Home-page: https://github.com/PetrKryze/phonemeRecognizerWrapper
Author: Petr Krýže
Author-email: Petr Krýže <petr.kryze@gmail.com>
License: MIT License
Project-URL: Homepage, https://github.com/PetrKryze/phonemeRecognizerWrapper
Project-URL: Bug Tracker, https://github.com/PetrKryze/phonemeRecognizerWrapper/issues
Keywords: phoneme,transcript,allosaurus,MATLAB,wrapper,recognizer
Classifier: Programming Language :: Python :: 3
Classifier: License :: OSI Approved :: MIT License
Classifier: Operating System :: OS Independent
Requires-Python: >=3.7
License-File: LICENSE.txt
Requires-Dist: allosaurus
Requires-Dist: pydub
Requires-Dist: setuptools
